mbdyn_lexer/__about__.py
mbdyn_lexer/__ini__.py
mbdyn_lexer/mbdynlexer.py
mbdyn_lexer-0.0.5.dist-info/METADATA
mbdyn_lexer-0.0.5.dist-info/WHEEL
mbdyn_lexer-0.0.5.dist-info/entry_points.txt
mbdyn_lexer-0.0.5.dist-info/licenses/LICENSE
mbdyn_lexer-0.0.5.dist-info/RECORD
